TwitchChatInterface/TwitchChatInterface.py
TwitchChatInterface/__init__.py
TwitchChatInterface/chat.py
TwitchChatInterface/conf.py
TwitchChatInterface/setup.py
TwitchChatInterface/lib/__init__.py
TwitchChatInterface/lib/events/__init__.py
TwitchChatInterface/lib/events/eventHandler.py
TwitchChatInterface/lib/twitchMessageHandler/__init__.py
TwitchChatInterface/lib/twitchMessageHandler/messageHandler.py
TwitchChatInterface/lib/twitchMessageHandler/parse.py
TwitchChatInterface/lib/twitchMessageHandler/modals/__init__.py
TwitchChatInterface/lib/twitchMessageHandler/modals/const.py
TwitchChatInterface/lib/twitchMessageHandler/modals/dataTypes.py
TwitchChatInterface_pkg_edog0049a-0.0.1.dist-info/LICENSE.txt
TwitchChatInterface_pkg_edog0049a-0.0.1.dist-info/METADATA
TwitchChatInterface_pkg_edog0049a-0.0.1.dist-info/WHEEL
TwitchChatInterface_pkg_edog0049a-0.0.1.dist-info/top_level.txt
TwitchChatInterface_pkg_edog0049a-0.0.1.dist-info/RECORD
